{
  "ButterPopcorn": "给爆米花加黄油",
  "ConvertPaperNapkinsToFunctionalAppliancesPaperNapkins": "将普通餐巾纸转换为功能电器专用餐巾纸",
  "CraftBlueberrySodaSyrup": "制作蓝莓苏打糖浆",
  "CraftBubblegumSodaSyrup": "制作泡泡糖苏打糖浆",
  "CraftColaSodaSyrup": "制作可乐苏打糖浆",
  "CraftDietColaSodaSyrup": "制作健怡可乐苏打糖浆",
  "CraftDrPeppaSodaSyrup": "制作胡椒博士苏打糖浆",
  "CraftEmptySodaSyrupBox": "制作空苏打糖浆盒",
  "CraftGingerAleSodaSyrup": "制作姜汁汽水苏打糖浆",
  "CraftGrapeSodaSyrup": "制作葡萄苏打糖浆",
  "CraftHomeBrewKeg": "制作家酿啤酒桶",
  "CraftKYColaSodaSyrup": "制作肯塔基可乐苏打糖浆",
  "CraftLemonLimeSodaSyrup": "制作柠檬青柠苏打糖浆",
  "CraftLimeSodaSyrup": "制作青柠苏打糖浆",
  "CraftMixedBerriesSodaSyrup": "制作混合浆果苏打糖浆",
  "CraftOrangeSodaSyrup": "制作橙子苏打糖浆",
  "CraftPineappleSodaSyrup": "制作菠萝苏打糖浆",
  "CraftRootBeerSodaSyrup": "制作根汁啤酒苏打糖浆",
  "CraftStrawberrySodaSyrup": "制作草莓苏打糖浆",
  "MakeBucketOfButteredPopcorn": "制作桶装黄油爆米花",
  "MakeBucketOfPopcorn": "制作桶装爆米花",
  "MakeEmptyCO2Tank": "制作空二氧化碳罐",
  "MakeEmptyKeg": "制作空啤酒桶",
  "RefillCO2Tank": "补充二氧化碳罐",
  "TakeButteredPopcornFromBucket": "从桶中取出黄油爆米花",
  "TakePopcornFromBucket": "从桶中取出爆米花",
  "WetPaperNapkins": "餐巾纸 (浸湿)"
}
