{
  "Sandbox_BanditsWeekOne": "匪徒第一周",
  "Sandbox_BanditsWeekOne.ArmyPopMultiplier": "NPC军队数量倍数",
  "Sandbox_BanditsWeekOne.BanditsPopMultiplier": "NPC匪徒数量倍数",
  "Sandbox_BanditsWeekOne.EventArson": "纵火事件",
  "Sandbox_BanditsWeekOne.EventBoeing": "波音飞机坠毁事件",
  "Sandbox_BanditsWeekOne.EventBombing": "喷气式轰炸机空袭",
  "Sandbox_BanditsWeekOne.EventFinalSolution": "最终解决方案事件 (核弹)",
  "Sandbox_BanditsWeekOne.EventGas": "喷气式飞机毒气攻击",
  "Sandbox_BanditsWeekOne.EventStrafe": "喷气式飞机扫射",
  "Sandbox_BanditsWeekOne.FiremanCooldown": "消防员冷却时间 [分钟]",
  "Sandbox_BanditsWeekOne.HazmatCooldown": "危险品处理人员冷却时间 [分钟]",
  "Sandbox_BanditsWeekOne.InhabitantsPistolChance": "NPC居民持有手枪的概率 [%]",
  "Sandbox_BanditsWeekOne.InhabitantsPopMultiplier": "NPC居民数量倍数",
  "Sandbox_BanditsWeekOne.MedicsCooldown": "医护人员冷却时间 [分钟]",
  "Sandbox_BanditsWeekOne.PoliceCooldown": "警察冷却时间 [分钟]",
  "Sandbox_BanditsWeekOne.PriceInflation": "每日价格通胀率",
  "Sandbox_BanditsWeekOne.PriceMultiplier": "购买价格倍数",
  "Sandbox_BanditsWeekOne.SWATCooldown": "特警冷却时间 [分钟]",
  "Sandbox_BanditsWeekOne.StartBabe": "开局带一个伙伴",
  "Sandbox_BanditsWeekOne.StartRide": "开局带一辆车 (可能性取决于 spawn 位置)",
  "Sandbox_BanditsWeekOne.StartTime": "结局前的时间",
  "Sandbox_BanditsWeekOne.StartTime_option1": "一周 (推荐)",
  "Sandbox_BanditsWeekOne.StartTime_option2": "两周",
  "Sandbox_BanditsWeekOne.StartTime_option3": "一个月",
  "Sandbox_BanditsWeekOne.StartTime_option4": "三个月",
  "Sandbox_BanditsWeekOne.StartTime_option5": "一年",
  "Sandbox_BanditsWeekOne.StartTime_option6": "十年",
  "Sandbox_BanditsWeekOne.StreetsPistolChance": "NPC路人持有手枪的概率 [%]",
  "Sandbox_BanditsWeekOne.StreetsPopMultiplier": "NPC路人数量倍数",
  "Sandbox_BanditsWeekOne.VehiclesMax": "同时存在的NPC驾驶车辆最大数量",
  "Sandbox_BanditsWeekOne.VehiclesSpeed": "NPC驾驶车辆速度倍数"
}
