{
  "IGUI_VehicleName89defender110": "89款路虎卫士110",
  "IGUI_VehicleName89defender110utility": "89款路虎卫士110多功能版",
  "IGUI_VehicleName89defender130": "89款路虎卫士130",
  "IGUI_VehicleName89defender90": "89款路虎卫士90",
  "IGUI_VehicleName89defender90utility": "89款路虎卫士90多功能版",
  "IGUI_VehicleName89defenderWolf": "89款路虎狼",
  "IGUI_VehicleNameTrailer89defender": "89款路虎拖车",
  "IGUI_VehiclePartDEF89Cage": "防滚架",
  "IGUI_VehiclePartDEF89CenterConsole": "中控台",
  "IGUI_VehiclePartDEF89Guards": "车灯护罩",
  "IGUI_VehiclePartDEF89Roof": "车顶",
  "IGUI_VehiclePartDEF89Roofrack": "车顶行李架",
  "IGUI_VehiclePartDEF89StorageLeft": "左侧储物箱",
  "IGUI_VehiclePartDEF89StorageRight": "右侧储物箱",
  "IGUI_VehiclePartDEF89TruckBedAddon": "货箱附加件",
  "IGUI_VehiclePartDEF89Trunk": "后备箱",
  "IGUI_VehiclePartDEF89Trunk130": "后备箱"
}
